LAP/__init__.py
LAP/__main__.py
LAP/modulos/__init__.py
LAP/modulos/paqadm.py
LAP/modulos/repoadm.py
LAP_latino_client-0.0.50.dist-info/LICENSE
LAP_latino_client-0.0.50.dist-info/METADATA
LAP_latino_client-0.0.50.dist-info/WHEEL
LAP_latino_client-0.0.50.dist-info/top_level.txt
LAP_latino_client-0.0.50.dist-info/RECORD
