Metadata-Version: 2.1
Name: LAP-latino-client
Version: 0.0.50
Summary: Administrador de paquetes de latino (LAP)
Author-email: Alvaro Martinez <alvarom12098@gmail.com>
Project-URL: Homepage, https://github.com/N3koSempai/LAP_Cliente
Project-URL: Bug Tracker, https://github.com/N3koSempai/LAP_Cliente/issues
Classifier: Development Status :: 2 - Pre-Alpha
Classifier: License :: OSI Approved :: GNU Affero General Public License v3 or later (AGPLv3+)
Classifier: Programming Language :: Python :: 3
Classifier: Intended Audience :: Education
Classifier: Intended Audience :: Developers
Classifier: Natural Language :: Spanish
Classifier: Operating System :: POSIX :: Linux
Classifier: Topic :: Software Development :: Libraries
Requires-Python: >=3.7
License-File: LICENSE
